autocfg/__init__.py
autocfg/annotate.py
autocfg/dataclasses.py
autocfg/type_check.py
autocfg-0.0.8.dist-info/LICENSE
autocfg-0.0.8.dist-info/METADATA
autocfg-0.0.8.dist-info/WHEEL
autocfg-0.0.8.dist-info/top_level.txt
autocfg-0.0.8.dist-info/RECORD
