Metadata-Version: 2.1
Name: autocfg
Version: 0.0.8
Summary: Deep learning configuration
Home-page: https://github.com/zhreshold/autocfg
Author: autocfg contributors
Author-email: autocfg@example.com
License: UNKNOWN
Platform: UNKNOWN
Classifier: Programming Language :: Python :: 3
Classifier: License :: OSI Approved :: MIT License
Classifier: Operating System :: OS Independent
Requires-Python: >=3.6
